fastapi_microsoft_identity/__init__.py
fastapi_microsoft_identity/auth_service.py
fastapi_microsoft_identity-0.1.6.dist-info/LICENSE
fastapi_microsoft_identity-0.1.6.dist-info/METADATA
fastapi_microsoft_identity-0.1.6.dist-info/WHEEL
fastapi_microsoft_identity-0.1.6.dist-info/top_level.txt
fastapi_microsoft_identity-0.1.6.dist-info/RECORD
