Metadata-Version: 2.1
Name: fastapi-microsoft-identity
Version: 0.1.6
Summary: Azure AD authentication for Fast API
Home-page: https://github.com/425Show/fastapi_microsoft_identity
Author: Christos Matskas
Author-email: christos.matskas@microsoft.com
License: MIT
Platform: UNKNOWN
Classifier: Development Status :: 2 - Pre-Alpha
Classifier: License :: OSI Approved :: MIT License
Classifier: Programming Language :: Python
Classifier: Programming Language :: Python :: 3
Classifier: Programming Language :: Python :: 3.7
Classifier: Programming Language :: Python :: 3.8
Classifier: Programming Language :: Python :: 3.9
Classifier: Programming Language :: Python :: 3.10
Requires-Dist: fastapi
Requires-Dist: httpx
Requires-Dist: requests
Requires-Dist: python-jose
Requires-Dist: pytest
Requires-Dist: multidict
